{
    "key": "group_5e4c2722257b8",
    "title": "Standard – Block: Subheading",
    "fields": [
        {
            "key": "field_5f20520c7f431",
            "label": "Overline",
            "name": "overline",
            "type": "text",
            "instructions": "",
            "required": 0,
            "conditional_logic": 0,
            "wrapper": {
                "width": "",
                "class": "",
                "id": ""
            },
            "wpml_cf_preferences": 0,
            "default_value": "",
            "placeholder": "",
            "prepend": "",
            "append": "",
            "maxlength": ""
        },
        {
            "key": "field_5e6fb510cc502",
            "label": "Subheading",
            "name": "headline",
            "type": "text",
            "instructions": "",
            "required": 1,
            "conditional_logic": 0,
            "wrapper": {
                "width": "",
                "class": "",
                "id": ""
            },
            "wpml_cf_preferences": 3,
            "hide_admin": 0,
            "default_value": "",
            "placeholder": "",
            "prepend": "",
            "append": "",
            "maxlength": ""
        },
        {
            "key": "field_5e6fb529cc503",
            "label": "Size",
            "name": "size",
            "type": "button_group",
            "instructions": "",
            "required": 0,
            "conditional_logic": 0,
            "wrapper": {
                "width": "",
                "class": "",
                "id": ""
            },
            "wpml_cf_preferences": 3,
            "hide_admin": 0,
            "choices": {
                "h2": "H2",
                "h3": "H3",
                "h4": "H4"
            },
            "allow_null": 0,
            "default_value": "",
            "layout": "horizontal",
            "return_format": "value"
        },
        {
            "key": "field_5e6fb5c0cc504",
            "label": "Indent",
            "name": "intend",
            "type": "true_false",
            "instructions": "",
            "required": 0,
            "conditional_logic": 0,
            "wrapper": {
                "width": "",
                "class": "",
                "id": ""
            },
            "wpml_cf_preferences": 3,
            "hide_admin": 0,
            "message": "",
            "default_value": 1,
            "ui": 1,
            "ui_on_text": "",
            "ui_off_text": ""
        }
    ],
    "location": [
        [
            {
                "param": "block",
                "operator": "==",
                "value": "acf\/standard-subheading"
            }
        ]
    ],
    "menu_order": 0,
    "position": "normal",
    "style": "default",
    "label_placement": "top",
    "instruction_placement": "label",
    "hide_on_screen": "",
    "active": true,
    "description": "",
    "modified": 1630190310
}